{"objects":{"20230318130413":{"geometries":[{"coordinates":[10.12382215,44.16348618],"id":"v_fenomeni_pub.fid--539f2bf9_186e9c4bc28_66e2","type":"Point","properties":{"data_bollettino":"2023-03-17Z","id_fenomeno":5,"id_bollettino":202303182,"lon":10.123822145398252,"id":null,"lat":44.16348617912355}},{"coordinates":[11.552502,43.99001438],"id":"v_fenomeni_pub.fid--539f2bf9_186e9c4bc28_66e3","type":"Point","properties":{"data_bollettino":"2023-03-17Z","id_fenomeno":5,"id_bollettino":202303182,"lon":11.552502001775302,"id":null,"lat":43.99001438027929}},{"coordinates":[10.8482232,43.52493724],"id":"v_fenomeni_pub.fid--539f2bf9_186e9c4bc28_66e4","type":"Point","properties":{"data_bollettino":"2023-03-17Z","id_fenomeno":5,"id_bollettino":202303182,"lon":10.848223199335454,"id":null,"lat":43.52493724243981}},{"coordinates":[11.73360227,44.60926743],"id":"v_fenomeni_pub.fid--539f2bf9_186e9c4bc28_66e5","type":"Point","properties":{"data_bollettino":"2023-03-17Z","id_fenomeno":5,"id_bollettino":202303182,"lon":11.7336022652596,"id":null,"lat":44.60926742792983}},{"coordinates":[10.36528916,45.29281053],"id":"v_fenomeni_pub.fid--539f2bf9_186e9c4bc28_66e6","type":"Point","properties":{"data_bollettino":"2023-03-17Z","id_fenomeno":5,"id_bollettino":202303182,"lon":10.365289163377321,"id":null,"lat":45.292810528978144}},{"coordinates":[12.05555829,42.5543078],"id":"v_fenomeni_pub.fid--539f2bf9_186e9c4bc28_66e7","type":"Point","properties":{"data_bollettino":"2023-03-17Z","id_fenomeno":5,"id_bollettino":202303182,"lon":12.05555828923169,"id":null,"lat":42.55430779820073}},{"coordinates":[12.86044835,43.49574991],"id":"v_fenomeni_pub.fid--539f2bf9_186e9c4bc28_66e8","type":"Point","properties":{"data_bollettino":"2023-03-17Z","id_fenomeno":5,"id_bollettino":202303182,"lon":12.860448349161915,"id":null,"lat":43.495749913868224}},{"coordinates":[11.75372452,43.27639511],"id":"v_fenomeni_pub.fid--539f2bf9_186e9c4bc28_66e9","type":"Point","properties":{"data_bollettino":"2023-03-17Z","id_fenomeno":1,"id_bollettino":202303182,"lon":11.753724516757856,"id":null,"lat":43.2763951081982}},{"coordinates":[13.00130411,42.43561285],"id":"v_fenomeni_pub.fid--539f2bf9_186e9c4bc28_66ea","type":"Point","properties":{"data_bollettino":"2023-03-17Z","id_fenomeno":1,"id_bollettino":202303182,"lon":13.001304109649704,"id":null,"lat":42.43561284956347}},{"coordinates":[11.17017922,42.62837773],"id":"v_fenomeni_pub.fid--539f2bf9_186e9c4bc28_66eb","type":"Point","properties":{"data_bollettino":"2023-03-17Z","id_fenomeno":1,"id_bollettino":202303182,"lon":11.170179223308445,"id":null,"lat":42.62837772697964}},{"coordinates":[12.49824782,44.07681385],"id":"v_fenomeni_pub.fid--539f2bf9_186e9c4bc28_66ec","type":"Point","properties":{"data_bollettino":"2023-03-17Z","id_fenomeno":1,"id_bollettino":202303182,"lon":12.498247822193314,"id":null,"lat":44.076813848959965}},{"coordinates":[10.60675618,44.76663177],"id":"v_fenomeni_pub.fid--539f2bf9_186e9c4bc28_66ed","type":"Point","properties":{"data_bollettino":"2023-03-17Z","id_fenomeno":1,"id_bollettino":202303182,"lon":10.606756181356388,"id":null,"lat":44.766631766929514}},{"coordinates":[8.95673156,45.43419067],"id":"v_fenomeni_pub.fid--539f2bf9_186e9c4bc28_66ee","type":"Point","properties":{"data_bollettino":"2023-03-17Z","id_fenomeno":1,"id_bollettino":202303182,"lon":8.956731558499248,"id":null,"lat":45.43419066566347}},{"coordinates":[10.1841889,45.94023404],"id":"v_fenomeni_pub.fid--539f2bf9_186e9c4bc28_66ef","type":"Point","properties":{"data_bollettino":"2023-03-17Z","id_fenomeno":1,"id_bollettino":202303182,"lon":10.184188899893021,"id":null,"lat":45.94023403656633}},{"coordinates":[11.17017922,45.15107707],"id":"v_fenomeni_pub.fid--539f2bf9_186e9c4bc28_66f0","type":"Point","properties":{"data_bollettino":"2023-03-17Z","id_fenomeno":1,"id_bollettino":202303182,"lon":11.170179223308445,"id":null,"lat":45.15107706518968}},{"coordinates":[11.53237975,46.21939144],"id":"v_fenomeni_pub.fid--539f2bf9_186e9c4bc28_66f1","type":"Point","properties":{"data_bollettino":"2023-03-17Z","id_fenomeno":1,"id_bollettino":202303182,"lon":11.532379750277045,"id":null,"lat":46.21939143785174}},{"coordinates":[9.64088811,44.73805187],"id":"v_fenomeni_pub.fid--539f2bf9_186e9c4bc28_66f2","type":"Point","properties":{"data_bollettino":"2023-03-17Z","id_fenomeno":1,"id_bollettino":202303182,"lon":9.64088810944012,"id":null,"lat":44.738051868381966}},{"coordinates":[9.09758732,46.02412956],"id":"v_fenomeni_pub.fid--539f2bf9_186e9c4bc28_66f3","type":"Point","properties":{"data_bollettino":"2023-03-17Z","id_fenomeno":1,"id_bollettino":202303182,"lon":9.09758731898722,"id":null,"lat":46.02412956024322}},{"coordinates":[7.68902971,45.78609537],"id":"v_fenomeni_pub.fid--539f2bf9_186e9c4bc28_66f4","type":"Point","properties":{"data_bollettino":"2023-03-17Z","id_fenomeno":1,"id_bollettino":202303182,"lon":7.689029714108787,"id":null,"lat":45.786095367409295}},{"coordinates":[7.16585118,44.99476215],"id":"v_fenomeni_pub.fid--539f2bf9_186e9c4bc28_66f5","type":"Point","properties":{"data_bollettino":"2023-03-17Z","id_fenomeno":1,"id_bollettino":202303182,"lon":7.1658511751539615,"id":null,"lat":44.99476214631839}},{"coordinates":[7.30670694,44.33644938],"id":"v_fenomeni_pub.fid--539f2bf9_186e9c4bc28_66f6","type":"Point","properties":{"data_bollettino":"2023-03-17Z","id_fenomeno":1,"id_bollettino":202303182,"lon":7.306706935641841,"id":null,"lat":44.33644937780499}},{"coordinates":[12.15616955,43.65610554],"id":"v_fenomeni_pub.fid--539f2bf9_186e9c4bc28_66f7","type":"Point","properties":{"data_bollettino":"2023-03-17Z","id_fenomeno":60,"id_bollettino":202303182,"lon":12.156169546722968,"id":null,"lat":43.656105535968365}},{"coordinates":[13.5446049,42.85005924],"id":"v_fenomeni_pub.fid--539f2bf9_186e9c4bc28_66f8","type":"Point","properties":{"data_bollettino":"2023-03-17Z","id_fenomeno":60,"id_bollettino":202303182,"lon":13.544604900102605,"id":null,"lat":42.85005923571463}},{"coordinates":[12.47812557,41.97354329],"id":"v_fenomeni_pub.fid--539f2bf9_186e9c4bc28_66f9","type":"Point","properties":{"data_bollettino":"2023-03-17Z","id_fenomeno":60,"id_bollettino":202303182,"lon":12.478125570695058,"id":null,"lat":41.973543294754485}},{"coordinates":[10.98907896,43.07094796],"id":"v_fenomeni_pub.fid--539f2bf9_186e9c4bc28_66fa","type":"Point","properties":{"data_bollettino":"2023-03-17Z","id_fenomeno":60,"id_bollettino":202303182,"lon":10.989078959823244,"id":null,"lat":43.070947957187556}},{"coordinates":[8.111597,45.09428474],"id":"v_fenomeni_pub.fid--539f2bf9_186e9c4bc28_66fb","type":"Point","properties":{"data_bollettino":"2023-03-17Z","id_fenomeno":60,"id_bollettino":202303182,"lon":8.111596995572333,"id":null,"lat":45.094284744763065}},{"coordinates":[11.53237975,40.32208182],"id":"v_fenomeni_pub.fid--539f2bf9_186e9c4bc28_66fc","type":"Point","properties":{"data_bollettino":"2023-03-17Z","id_fenomeno":40,"id_bollettino":202303182,"lon":11.532379750277045,"id":null,"lat":40.32208181988213}},{"coordinates":[10.36528916,39.62818523],"id":"v_fenomeni_pub.fid--539f2bf9_186e9c4bc28_66fd","type":"Point","properties":{"data_bollettino":"2023-03-17Z","id_fenomeno":40,"id_bollettino":202303182,"lon":10.365289163377321,"id":null,"lat":39.62818522601206}},{"coordinates":[11.99519153,40.27604137],"id":"v_fenomeni_pub.fid--539f2bf9_186e9c4bc28_66fe","type":"Point","properties":{"data_bollettino":"2023-03-17Z","id_fenomeno":51,"id_bollettino":202303182,"lon":11.995191534736923,"id":null,"lat":40.276041371606965}},{"coordinates":[10.76773419,39.69015005],"id":"v_fenomeni_pub.fid--539f2bf9_186e9c4bc28_66ff","type":"Point","properties":{"data_bollettino":"2023-03-17Z","id_fenomeno":51,"id_bollettino":202303182,"lon":10.767734193342433,"id":null,"lat":39.69015004901579}}],"type":"GeometryCollection"}},"type":"Topology","arcs":[]}