{"type":"FeatureCollection","totalFeatures":69,"features":[{"type":"Feature","id":"v_fenomeni_pub.fid-3feb16c1_17e2541ac8c_2f7d","geometry":{"type":"Point","coordinates":[13.24277113,46.40008648]},"geometry_name":"geom","properties":{"id":null,"id_bollettino":202201051,"data_bollettino":"2022-01-04Z","id_fenomeno":4,"lat":46.40008647535587,"lon":13.24277112762877}},{"type":"Feature","id":"v_fenomeni_pub.fid-3feb16c1_17e2541ac8c_2f7e","geometry":{"type":"Point","coordinates":[12.1360473,46.53867679]},"geometry_name":"geom","properties":{"id":null,"id_bollettino":202201051,"data_bollettino":"2022-01-04Z","id_fenomeno":4,"lat":46.53867678647957,"lon":12.136047295224714}},{"type":"Feature","id":"v_fenomeni_pub.fid-3feb16c1_17e2541ac8c_2f7f","geometry":{"type":"Point","coordinates":[11.87445803,45.92623909]},"geometry_name":"geom","properties":{"id":null,"id_bollettino":202201051,"data_bollettino":"2022-01-04Z","id_fenomeno":4,"lat":45.926239089165264,"lon":11.874458025747389}},{"type":"Feature","id":"v_fenomeni_pub.fid-3feb16c1_17e2541ac8c_2f80","geometry":{"type":"Point","coordinates":[12.51837007,46.26114324]},"geometry_name":"geom","properties":{"id":null,"id_bollettino":202201051,"data_bollettino":"2022-01-04Z","id_fenomeno":4,"lat":46.26114324052908,"lon":12.518370073691568}},{"type":"Feature","id":"v_fenomeni_pub.fid-3feb16c1_17e2541ac8c_2f81","geometry":{"type":"Point","coordinates":[11.29091273,45.58930075]},"geometry_name":"geom","properties":{"id":null,"id_bollettino":202201051,"data_bollettino":"2022-01-04Z","id_fenomeno":3,"lat":45.58930074986824,"lon":11.290912732297977}},{"type":"Feature","id":"v_fenomeni_pub.fid-3feb16c1_17e2541ac8c_2f82","geometry":{"type":"Point","coordinates":[10.94883446,46.10789796]},"geometry_name":"geom","properties":{"id":null,"id_bollettino":202201051,"data_bollettino":"2022-01-04Z","id_fenomeno":3,"lat":46.10789796062404,"lon":10.948834456826734}},{"type":"Feature","id":"v_fenomeni_pub.fid-3feb16c1_17e2541ac8c_2f83","geometry":{"type":"Point","coordinates":[10.82810095,46.67691426]},"geometry_name":"geom","properties":{"id":null,"id_bollettino":202201051,"data_bollettino":"2022-01-04Z","id_fenomeno":3,"lat":46.676914261531415,"lon":10.8281009478372}},{"type":"Feature","id":"v_fenomeni_pub.fid-3feb16c1_17e2541ac8c_2f84","geometry":{"type":"Point","coordinates":[11.49213525,46.88360912]},"geometry_name":"geom","properties":{"id":null,"id_bollettino":202201051,"data_bollettino":"2022-01-04Z","id_fenomeno":3,"lat":46.8836091178504,"lon":11.492135247280533}},{"type":"Feature","id":"v_fenomeni_pub.fid-3feb16c1_17e2541ac8c_2f85","geometry":{"type":"Point","coordinates":[11.5927465,46.38620803]},"geometry_name":"geom","properties":{"id":null,"id_bollettino":202201051,"data_bollettino":"2022-01-04Z","id_fenomeno":3,"lat":46.386208034816114,"lon":11.592746504771812}},{"type":"Feature","id":"v_fenomeni_pub.fid-3feb16c1_17e2541ac8c_2f86","geometry":{"type":"Point","coordinates":[9.62076586,44.59494038]},"geometry_name":"geom","properties":{"id":null,"id_bollettino":202201051,"data_bollettino":"2022-01-04Z","id_fenomeno":3,"lat":44.59494037969259,"lon":9.620765857941864}},{"type":"Feature","id":"v_fenomeni_pub.fid-3feb16c1_17e2541ac8c_2f87","geometry":{"type":"Point","coordinates":[10.52626718,44.33644938]},"geometry_name":"geom","properties":{"id":null,"id_bollettino":202201051,"data_bollettino":"2022-01-04Z","id_fenomeno":3,"lat":44.33644937780499,"lon":10.526267175363367}},{"type":"Feature","id":"v_fenomeni_pub.fid-3feb16c1_17e2541ac8c_2f88","geometry":{"type":"Point","coordinates":[11.5122575,44.23561599]},"geometry_name":"geom","properties":{"id":null,"id_bollettino":202201051,"data_bollettino":"2022-01-04Z","id_fenomeno":3,"lat":44.235615992664215,"lon":11.512257498778787}},{"type":"Feature","id":"v_fenomeni_pub.fid-3feb16c1_17e2541ac8c_2f89","geometry":{"type":"Point","coordinates":[13.22264888,45.87022398]},"geometry_name":"geom","properties":{"id":null,"id_bollettino":202201051,"data_bollettino":"2022-01-04Z","id_fenomeno":2,"lat":45.87022398285129,"lon":13.222648876130515}},{"type":"Feature","id":"v_fenomeni_pub.fid-3feb16c1_17e2541ac8c_2f8a","geometry":{"type":"Point","coordinates":[12.15616955,45.4059429]},"geometry_name":"geom","properties":{"id":null,"id_bollettino":202201051,"data_bollettino":"2022-01-04Z","id_fenomeno":2,"lat":45.405942903555946,"lon":12.156169546722968}},{"type":"Feature","id":"v_fenomeni_pub.fid-3feb16c1_17e2541ac8c_2f8b","geometry":{"type":"Point","coordinates":[12.23665855,44.85228666]},"geometry_name":"geom","properties":{"id":null,"id_bollettino":202201051,"data_bollettino":"2022-01-04Z","id_fenomeno":1,"lat":44.85228666186993,"lon":12.236658552715992}},{"type":"Feature","id":"v_fenomeni_pub.fid-3feb16c1_17e2541ac8c_2f8c","geometry":{"type":"Point","coordinates":[10.72748969,45.16526631]},"geometry_name":"geom","properties":{"id":null,"id_bollettino":202201051,"data_bollettino":"2022-01-04Z","id_fenomeno":1,"lat":45.16526631174155,"lon":10.727489690345921}},{"type":"Feature","id":"v_fenomeni_pub.fid-3feb16c1_17e2541ac8c_2f8d","geometry":{"type":"Point","coordinates":[10.06345539,44.88081003]},"geometry_name":"geom","properties":{"id":null,"id_bollettino":202201051,"data_bollettino":"2022-01-04Z","id_fenomeno":1,"lat":44.88081002630368,"lon":10.063455390903487}},{"type":"Feature","id":"v_fenomeni_pub.fid-3feb16c1_17e2541ac8c_2f8e","geometry":{"type":"Point","coordinates":[11.41164624,44.79519753]},"geometry_name":"geom","properties":{"id":null,"id_bollettino":202201051,"data_bollettino":"2022-01-04Z","id_fenomeno":1,"lat":44.7951975320962,"lon":11.411646241287512}},{"type":"Feature","id":"v_fenomeni_pub.fid-3feb16c1_17e2541ac8c_2f8f","geometry":{"type":"Point","coordinates":[12.45800332,43.87408401]},"geometry_name":"geom","properties":{"id":null,"id_bollettino":202201051,"data_bollettino":"2022-01-04Z","id_fenomeno":1,"lat":43.874084006988646,"lon":12.458003319196802}},{"type":"Feature","id":"v_fenomeni_pub.fid-3feb16c1_17e2541ac8c_2f90","geometry":{"type":"Point","coordinates":[12.8805706,43.11503053]},"geometry_name":"geom","properties":{"id":null,"id_bollettino":202201051,"data_bollettino":"2022-01-04Z","id_fenomeno":1,"lat":43.115030527779524,"lon":12.88057060066017}},{"type":"Feature","id":"v_fenomeni_pub.fid-3feb16c1_17e2541ac8c_2f91","geometry":{"type":"Point","coordinates":[13.5446049,42.03335503]},"geometry_name":"geom","properties":{"id":null,"id_bollettino":202201051,"data_bollettino":"2022-01-04Z","id_fenomeno":1,"lat":42.033355033645385,"lon":13.544604900102605}},{"type":"Feature","id":"v_fenomeni_pub.fid-3feb16c1_17e2541ac8c_2f92","geometry":{"type":"Point","coordinates":[14.40986171,41.62853517]},"geometry_name":"geom","properties":{"id":null,"id_bollettino":202201051,"data_bollettino":"2022-01-04Z","id_fenomeno":1,"lat":41.62853516699102,"lon":14.409861714528493}},{"type":"Feature","id":"v_fenomeni_pub.fid-3feb16c1_17e2541ac8c_2f93","geometry":{"type":"Point","coordinates":[14.38973946,40.91774932]},"geometry_name":"geom","properties":{"id":null,"id_bollettino":202201051,"data_bollettino":"2022-01-04Z","id_fenomeno":1,"lat":40.91774931638699,"lon":14.38973946303024}},{"type":"Feature","id":"v_fenomeni_pub.fid-3feb16c1_17e2541ac8c_2f94","geometry":{"type":"Point","coordinates":[13.36350464,41.52316413]},"geometry_name":"geom","properties":{"id":null,"id_bollettino":202201051,"data_bollettino":"2022-01-04Z","id_fenomeno":1,"lat":41.52316412777825,"lon":13.363504636618304}},{"type":"Feature","id":"v_fenomeni_pub.fid-3feb16c1_17e2541ac8c_2f95","geometry":{"type":"Point","coordinates":[12.2567808,42.1528098]},"geometry_name":"geom","properties":{"id":null,"id_bollettino":202201051,"data_bollettino":"2022-01-04Z","id_fenomeno":1,"lat":42.15280980180548,"lon":12.256780804214245}},{"type":"Feature","id":"v_fenomeni_pub.fid-3feb16c1_17e2541ac8c_2f96","geometry":{"type":"Point","coordinates":[11.31103498,42.85005924]},"geometry_name":"geom","properties":{"id":null,"id_bollettino":202201051,"data_bollettino":"2022-01-04Z","id_fenomeno":1,"lat":42.85005923571463,"lon":11.311034983796233}},{"type":"Feature","id":"v_fenomeni_pub.fid-3feb16c1_17e2541ac8c_2f97","geometry":{"type":"Point","coordinates":[10.52626718,43.65610554]},"geometry_name":"geom","properties":{"id":null,"id_bollettino":202201051,"data_bollettino":"2022-01-04Z","id_fenomeno":1,"lat":43.656105535968365,"lon":10.526267175363367}},{"type":"Feature","id":"v_fenomeni_pub.fid-3feb16c1_17e2541ac8c_2f98","geometry":{"type":"Point","coordinates":[9.80186612,44.22119709]},"geometry_name":"geom","properties":{"id":null,"id_bollettino":202201051,"data_bollettino":"2022-01-04Z","id_fenomeno":1,"lat":44.22119709417171,"lon":9.801866121426162}},{"type":"Feature","id":"v_fenomeni_pub.fid-3feb16c1_17e2541ac8c_2f99","geometry":{"type":"Point","coordinates":[11.53237975,43.52493724]},"geometry_name":"geom","properties":{"id":null,"id_bollettino":202201051,"data_bollettino":"2022-01-04Z","id_fenomeno":1,"lat":43.52493724243981,"lon":11.532379750277045}},{"type":"Feature","id":"v_fenomeni_pub.fid-3feb16c1_17e2541ac8c_2f9a","geometry":{"type":"Point","coordinates":[12.27690306,42.79102166]},"geometry_name":"geom","properties":{"id":null,"id_bollettino":202201051,"data_bollettino":"2022-01-04Z","id_fenomeno":1,"lat":42.791021664550975,"lon":12.276903055712504}},{"type":"Feature","id":"v_fenomeni_pub.fid-3feb16c1_17e2541ac8c_2f9b","geometry":{"type":"Point","coordinates":[8.8561203,40.70453119]},"geometry_name":"geom","properties":{"id":null,"id_bollettino":202201051,"data_bollettino":"2022-01-04Z","id_fenomeno":1,"lat":40.70453118910188,"lon":8.856120301007973}},{"type":"Feature","id":"v_fenomeni_pub.fid-3feb16c1_17e2541ac8c_2f9c","geometry":{"type":"Point","coordinates":[8.87624255,40.04536875]},"geometry_name":"geom","properties":{"id":null,"id_bollettino":202201051,"data_bollettino":"2022-01-04Z","id_fenomeno":1,"lat":40.045368753522766,"lon":8.876242552506227}},{"type":"Feature","id":"v_fenomeni_pub.fid-3feb16c1_17e2541ac8c_2f9d","geometry":{"type":"Point","coordinates":[10.1841889,44.0623561]},"geometry_name":"geom","properties":{"id":null,"id_bollettino":202201051,"data_bollettino":"2022-01-04Z","id_fenomeno":5,"lat":44.062356099573755,"lon":10.184188899893021}},{"type":"Feature","id":"v_fenomeni_pub.fid-3feb16c1_17e2541ac8c_2f9e","geometry":{"type":"Point","coordinates":[10.96895671,44.80947511]},"geometry_name":"geom","properties":{"id":null,"id_bollettino":202201051,"data_bollettino":"2022-01-04Z","id_fenomeno":5,"lat":44.809475114627496,"lon":10.96895670832499}},{"type":"Feature","id":"v_fenomeni_pub.fid-3feb16c1_17e2541ac8c_2f9f","geometry":{"type":"Point","coordinates":[12.39763656,45.17945202]},"geometry_name":"geom","properties":{"id":null,"id_bollettino":202201051,"data_bollettino":"2022-01-04Z","id_fenomeno":5,"lat":45.17945202488955,"lon":12.397636564702037}},{"type":"Feature","id":"v_fenomeni_pub.fid-3feb16c1_17e2541ac8c_2fa0","geometry":{"type":"Point","coordinates":[8.03110799,45.0516534]},"geometry_name":"geom","properties":{"id":null,"id_bollettino":202201051,"data_bollettino":"2022-01-04Z","id_fenomeno":62,"lat":45.05165340331521,"lon":8.031107989579223}},{"type":"Feature","id":"v_fenomeni_pub.fid-3feb16c1_17e2541ac8c_2fa1","geometry":{"type":"Point","coordinates":[10.92871221,44.52325214]},"geometry_name":"geom","properties":{"id":null,"id_bollettino":202201051,"data_bollettino":"2022-01-04Z","id_fenomeno":62,"lat":44.523252142386205,"lon":10.928712205328479}},{"type":"Feature","id":"v_fenomeni_pub.fid-3feb16c1_17e2541ac8c_2fa2","geometry":{"type":"Point","coordinates":[9.21832083,41.19087949]},"geometry_name":"geom","properties":{"id":null,"id_bollettino":202201051,"data_bollettino":"2022-01-04Z","id_fenomeno":11,"lat":41.19087949014338,"lon":9.21832082797675}},{"type":"Feature","id":"v_fenomeni_pub.fid-3feb16c1_17e2541ac8c_2fa3","geometry":{"type":"Point","coordinates":[12.8805706,45.56113071]},"geometry_name":"geom","properties":{"id":null,"id_bollettino":202201051,"data_bollettino":"2022-01-04Z","id_fenomeno":11,"lat":45.561130712113204,"lon":12.88057060066017}},{"type":"Feature","id":"v_fenomeni_pub.fid-3feb16c1_17e2541ac8c_2fa4","geometry":{"type":"Point","coordinates":[12.43788107,44.5089039]},"geometry_name":"geom","properties":{"id":null,"id_bollettino":202201051,"data_bollettino":"2022-01-04Z","id_fenomeno":11,"lat":44.5089038958914,"lon":12.437881067698546}},{"type":"Feature","id":"v_fenomeni_pub.fid-3feb16c1_17e2541ac8c_2fa5","geometry":{"type":"Point","coordinates":[12.43788107,43.49574991]},"geometry_name":"geom","properties":{"id":null,"id_bollettino":202201051,"data_bollettino":"2022-01-04Z","id_fenomeno":11,"lat":43.495749913868224,"lon":12.437881067698546}},{"type":"Feature","id":"v_fenomeni_pub.fid-3feb16c1_17e2541ac8c_2fa6","geometry":{"type":"Point","coordinates":[13.14215987,42.46530771]},"geometry_name":"geom","properties":{"id":null,"id_bollettino":202201051,"data_bollettino":"2022-01-04Z","id_fenomeno":11,"lat":42.465307705851295,"lon":13.142159870137494}},{"type":"Feature","id":"v_fenomeni_pub.fid-3feb16c1_17e2541ac8c_2fa7","geometry":{"type":"Point","coordinates":[14.00741668,41.74874867]},"geometry_name":"geom","properties":{"id":null,"id_bollettino":202201051,"data_bollettino":"2022-01-04Z","id_fenomeno":11,"lat":41.74874866644179,"lon":14.007416684562484}},{"type":"Feature","id":"v_fenomeni_pub.fid-3feb16c1_17e2541ac8c_2fa8","geometry":{"type":"Point","coordinates":[9.62076586,39.96830379]},"geometry_name":"geom","properties":{"id":null,"id_bollettino":202201051,"data_bollettino":"2022-01-04Z","id_fenomeno":11,"lat":39.96830378967768,"lon":9.620765857941864}},{"type":"Feature","id":"v_fenomeni_pub.fid-3feb16c1_17e2541ac8c_2fa9","geometry":{"type":"Point","coordinates":[8.31281951,44.29325626]},"geometry_name":"geom","properties":{"id":null,"id_bollettino":202201051,"data_bollettino":"2022-01-04Z","id_fenomeno":10,"lat":44.29325626411933,"lon":8.31281951055489}},{"type":"Feature","id":"v_fenomeni_pub.fid-3feb16c1_17e2541ac8c_2faa","geometry":{"type":"Point","coordinates":[10.94883446,42.65798105]},"geometry_name":"geom","properties":{"id":null,"id_bollettino":202201051,"data_bollettino":"2022-01-04Z","id_fenomeno":10,"lat":42.65798105002814,"lon":10.948834456826734}},{"type":"Feature","id":"v_fenomeni_pub.fid-3feb16c1_17e2541ac8c_2fab","geometry":{"type":"Point","coordinates":[13.98729443,40.75027846]},"geometry_name":"geom","properties":{"id":null,"id_bollettino":202201051,"data_bollettino":"2022-01-04Z","id_fenomeno":10,"lat":40.750278461713314,"lon":13.987294433064228}},{"type":"Feature","id":"v_fenomeni_pub.fid-3feb16c1_17e2541ac8c_2fac","geometry":{"type":"Point","coordinates":[18.21296725,40.10695807]},"geometry_name":"geom","properties":{"id":null,"id_bollettino":202201051,"data_bollettino":"2022-01-04Z","id_fenomeno":10,"lat":40.10695807311529,"lon":18.2129672476997}},{"type":"Feature","id":"v_fenomeni_pub.fid-3feb16c1_17e2541ac8c_2fad","geometry":{"type":"Point","coordinates":[12.86044835,37.74352449]},"geometry_name":"geom","properties":{"id":null,"id_bollettino":202201051,"data_bollettino":"2022-01-04Z","id_fenomeno":10,"lat":37.743524486314215,"lon":12.860448349161915}},{"type":"Feature","id":"v_fenomeni_pub.fid-3feb16c1_17e2541ac8c_2fae","geometry":{"type":"Point","coordinates":[7.66890746,40.19923758]},"geometry_name":"geom","properties":{"id":null,"id_bollettino":202201051,"data_bollettino":"2022-01-04Z","id_fenomeno":41,"lat":40.199237584684205,"lon":7.668907462610531}},{"type":"Feature","id":"v_fenomeni_pub.fid-3feb16c1_17e2541ac8c_2faf","geometry":{"type":"Point","coordinates":[7.4878072,41.80877117]},"geometry_name":"geom","properties":{"id":null,"id_bollettino":202201051,"data_bollettino":"2022-01-04Z","id_fenomeno":41,"lat":41.80877116541478,"lon":7.487807199126231}},{"type":"Feature","id":"v_fenomeni_pub.fid-3feb16c1_17e2541ac8c_2fb0","geometry":{"type":"Point","coordinates":[9.21832083,38.14025042]},"geometry_name":"geom","properties":{"id":null,"id_bollettino":202201051,"data_bollettino":"2022-01-04Z","id_fenomeno":41,"lat":38.14025041792851,"lon":9.21832082797675}},{"type":"Feature","id":"v_fenomeni_pub.fid-3feb16c1_17e2541ac8c_2fb1","geometry":{"type":"Point","coordinates":[10.28480016,38.97420559]},"geometry_name":"geom","properties":{"id":null,"id_bollettino":202201051,"data_bollettino":"2022-01-04Z","id_fenomeno":41,"lat":38.974205594215086,"lon":10.2848001573843}},{"type":"Feature","id":"v_fenomeni_pub.fid-3feb16c1_17e2541ac8c_2fb2","geometry":{"type":"Point","coordinates":[10.48602267,40.88733154]},"geometry_name":"geom","properties":{"id":null,"id_bollettino":202201051,"data_bollettino":"2022-01-04Z","id_fenomeno":41,"lat":40.88733153842093,"lon":10.486022672366854}},{"type":"Feature","id":"v_fenomeni_pub.fid-3feb16c1_17e2541ac8c_2fb3","geometry":{"type":"Point","coordinates":[13.16319552,45.2665047]},"geometry_name":"geom","properties":{"id":null,"id_bollettino":202201051,"data_bollettino":"2022-01-04Z","id_fenomeno":41,"lat":45.26650469790152,"lon":13.163195523551039}},{"type":"Feature","id":"v_fenomeni_pub.fid-3feb16c1_17e2541ac8c_2fb4","geometry":{"type":"Point","coordinates":[14.2497971,43.96311125]},"geometry_name":"geom","properties":{"id":null,"id_bollettino":202201051,"data_bollettino":"2022-01-04Z","id_fenomeno":40,"lat":43.963111254106465,"lon":14.249797104456846}},{"type":"Feature","id":"v_fenomeni_pub.fid-3feb16c1_17e2541ac8c_2fb5","geometry":{"type":"Point","coordinates":[15.41688769,42.60086521]},"geometry_name":"geom","properties":{"id":null,"id_bollettino":202201051,"data_bollettino":"2022-01-04Z","id_fenomeno":40,"lat":42.60086520933003,"lon":15.416887691356568}},{"type":"Feature","id":"v_fenomeni_pub.fid-3feb16c1_17e2541ac8c_2fb6","geometry":{"type":"Point","coordinates":[17.67057986,41.35938019]},"geometry_name":"geom","properties":{"id":null,"id_bollettino":202201051,"data_bollettino":"2022-01-04Z","id_fenomeno":40,"lat":41.35938019020575,"lon":17.670579859161194}},{"type":"Feature","id":"v_fenomeni_pub.fid-3feb16c1_17e2541ac8c_2fb7","geometry":{"type":"Point","coordinates":[17.63033536,39.6148882]},"geometry_name":"geom","properties":{"id":null,"id_bollettino":202201051,"data_bollettino":"2022-01-04Z","id_fenomeno":40,"lat":39.61488820011688,"lon":17.630335356164682}},{"type":"Feature","id":"v_fenomeni_pub.fid-3feb16c1_17e2541ac8c_2fb8","geometry":{"type":"Point","coordinates":[16.80532304,37.52269158]},"geometry_name":"geom","properties":{"id":null,"id_bollettino":202201051,"data_bollettino":"2022-01-04Z","id_fenomeno":40,"lat":37.52269158472237,"lon":16.805323044736202}},{"type":"Feature","id":"v_fenomeni_pub.fid-3feb16c1_17e2541ac8c_2fb9","geometry":{"type":"Point","coordinates":[15.73884372,36.17012733]},"geometry_name":"geom","properties":{"id":null,"id_bollettino":202201051,"data_bollettino":"2022-01-04Z","id_fenomeno":40,"lat":36.170127330348116,"lon":15.738843715328654}},{"type":"Feature","id":"v_fenomeni_pub.fid-3feb16c1_17e2541ac8c_2fba","geometry":{"type":"Point","coordinates":[13.00221751,36.65593108]},"geometry_name":"geom","properties":{"id":null,"id_bollettino":202201051,"data_bollettino":"2022-01-04Z","id_fenomeno":40,"lat":36.655931079753366,"lon":13.002217511564996}},{"type":"Feature","id":"v_fenomeni_pub.fid-3feb16c1_17e2541ac8c_2fbb","geometry":{"type":"Point","coordinates":[11.19121488,37.85708133]},"geometry_name":"geom","properties":{"id":null,"id_bollettino":202201051,"data_bollettino":"2022-01-04Z","id_fenomeno":40,"lat":37.85708132910506,"lon":11.191214876721093}},{"type":"Feature","id":"v_fenomeni_pub.fid-3feb16c1_17e2541ac8c_2fbc","geometry":{"type":"Point","coordinates":[13.84735207,39.24186226]},"geometry_name":"geom","properties":{"id":null,"id_bollettino":202201051,"data_bollettino":"2022-01-04Z","id_fenomeno":40,"lat":39.24186225989307,"lon":13.847352074491731}},{"type":"Feature","id":"v_fenomeni_pub.fid-3feb16c1_17e2541ac8c_2fbd","geometry":{"type":"Point","coordinates":[11.59365991,39.84701441]},"geometry_name":"geom","properties":{"id":null,"id_bollettino":202201051,"data_bollettino":"2022-01-04Z","id_fenomeno":40,"lat":39.84701440650949,"lon":11.593659906686206}},{"type":"Feature","id":"v_fenomeni_pub.fid-3feb16c1_17e2541ac8c_2fbe","geometry":{"type":"Point","coordinates":[12.55952798,40.79815902]},"geometry_name":"geom","properties":{"id":null,"id_bollettino":202201051,"data_bollettino":"2022-01-04Z","id_fenomeno":40,"lat":40.798159020443464,"lon":12.559527978603374}},{"type":"Feature","id":"v_fenomeni_pub.fid-3feb16c1_17e2541ac8c_2fbf","geometry":{"type":"Point","coordinates":[11.11072587,41.93077498]},"geometry_name":"geom","properties":{"id":null,"id_bollettino":202201051,"data_bollettino":"2022-01-04Z","id_fenomeno":40,"lat":41.93077497876197,"lon":11.110725870728071}},{"type":"Feature","id":"v_fenomeni_pub.fid-3feb16c1_17e2541ac8c_2fc0","geometry":{"type":"Point","coordinates":[9.58143476,43.83261465]},"geometry_name":"geom","properties":{"id":null,"id_bollettino":202201051,"data_bollettino":"2022-01-04Z","id_fenomeno":40,"lat":43.83261465469094,"lon":9.581434756860647}},{"type":"Feature","id":"v_fenomeni_pub.fid-3feb16c1_17e2541ac8c_2fc1","geometry":{"type":"Point","coordinates":[8.1929994,43.61448486]},"geometry_name":"geom","properties":{"id":null,"id_bollettino":202201051,"data_bollettino":"2022-01-04Z","id_fenomeno":40,"lat":43.614484855658034,"lon":8.19299940348038}}],"crs":{"type":"name","properties":{"name":"urn:ogc:def:crs:EPSG::4326"}}}