{"type":"FeatureCollection","totalFeatures":2,"features":[{"type":"Feature","id":"v_fenomeni_pub.fid--40854dee_19416edc459_-78f9","geometry":{"type":"Point","coordinates":[10.00308864,45.08007783]},"geometry_name":"geom","properties":{"id":null,"id_bollettino":202412301,"data_bollettino":"2024-12-30Z","id_fenomeno":30,"lat":45.08007783106414,"lon":10.00308863640872}},{"type":"Feature","id":"v_fenomeni_pub.fid--40854dee_19416edc459_-78f8","geometry":{"type":"Point","coordinates":[11.75372452,45.15107707]},"geometry_name":"geom","properties":{"id":null,"id_bollettino":202412301,"data_bollettino":"2024-12-30Z","id_fenomeno":30,"lat":45.15107706518968,"lon":11.753724516757856}}],"crs":{"type":"name","properties":{"name":"urn:ogc:def:crs:EPSG::4326"}}}