{"type":"FeatureCollection","totalFeatures":43,"features":[{"type":"Feature","id":"v_fenomeni_pub.fid--3eced7c9_19ca8b69bf0_-cc9","geometry":{"type":"Point","coordinates":[8.81747083,39.64584285]},"geometry_name":"geom","properties":{"id":null,"id_bollettino":202603032,"data_bollettino":"2026-03-03Z","id_fenomeno":5,"lat":39.645842852903556,"lon":8.81747082519057}},{"type":"Feature","id":"v_fenomeni_pub.fid--3eced7c9_19ca8b69bf0_-cc8","geometry":{"type":"Point","coordinates":[8.75710407,40.43152395]},"geometry_name":"geom","properties":{"id":null,"id_bollettino":202603032,"data_bollettino":"2026-03-03Z","id_fenomeno":5,"lat":40.431523946191916,"lon":8.757104070695805}},{"type":"Feature","id":"v_fenomeni_pub.fid--3eced7c9_19ca8b69bf0_-cc7","geometry":{"type":"Point","coordinates":[9.58211638,40.03211181]},"geometry_name":"geom","properties":{"id":null,"id_bollettino":202603032,"data_bollettino":"2026-03-03Z","id_fenomeno":5,"lat":40.03211181200739,"lon":9.582116382124642}},{"type":"Feature","id":"v_fenomeni_pub.fid--3eced7c9_19ca8b69bf0_-cc6","geometry":{"type":"Point","coordinates":[8.5357593,40.01670278]},"geometry_name":"geom","properties":{"id":null,"id_bollettino":202603032,"data_bollettino":"2026-03-03Z","id_fenomeno":1,"lat":40.01670278444187,"lon":8.535759304214903}},{"type":"Feature","id":"v_fenomeni_pub.fid--3eced7c9_19ca8b69bf0_-cc5","geometry":{"type":"Point","coordinates":[9.28028261,39.38194016]},"geometry_name":"geom","properties":{"id":null,"id_bollettino":202603032,"data_bollettino":"2026-03-03Z","id_fenomeno":1,"lat":39.381940159389465,"lon":9.280282609650808}},{"type":"Feature","id":"v_fenomeni_pub.fid--3eced7c9_19ca8b69bf0_-cc4","geometry":{"type":"Point","coordinates":[9.32052711,40.72191098]},"geometry_name":"geom","properties":{"id":null,"id_bollettino":202603032,"data_bollettino":"2026-03-03Z","id_fenomeno":1,"lat":40.72191097533901,"lon":9.320527112647321}},{"type":"Feature","id":"v_fenomeni_pub.fid--3eced7c9_19ca8b69bf0_-cc3","geometry":{"type":"Point","coordinates":[11.29250776,42.7487676]},"geometry_name":"geom","properties":{"id":null,"id_bollettino":202603032,"data_bollettino":"2026-03-03Z","id_fenomeno":1,"lat":42.74876760407136,"lon":11.29250775947637}},{"type":"Feature","id":"v_fenomeni_pub.fid--3eced7c9_19ca8b69bf0_-cc2","geometry":{"type":"Point","coordinates":[12.07727557,42.30388765]},"geometry_name":"geom","properties":{"id":null,"id_bollettino":202603032,"data_bollettino":"2026-03-03Z","id_fenomeno":1,"lat":42.303887649299796,"lon":12.077275567909236}},{"type":"Feature","id":"v_fenomeni_pub.fid--3eced7c9_19ca8b69bf0_-cc1","geometry":{"type":"Point","coordinates":[12.88216563,42.46737815]},"geometry_name":"geom","properties":{"id":null,"id_bollettino":202603032,"data_bollettino":"2026-03-03Z","id_fenomeno":1,"lat":42.467378146970375,"lon":12.88216562783946}},{"type":"Feature","id":"v_fenomeni_pub.fid--3eced7c9_19ca8b69bf0_-cc0","geometry":{"type":"Point","coordinates":[12.29862033,42.95529355]},"geometry_name":"geom","properties":{"id":null,"id_bollettino":202603032,"data_bollettino":"2026-03-03Z","id_fenomeno":1,"lat":42.955293553595745,"lon":12.298620334390048}},{"type":"Feature","id":"v_fenomeni_pub.fid--3eced7c9_19ca8b69bf0_-cbf","geometry":{"type":"Point","coordinates":[13.10351039,43.27843852]},"geometry_name":"geom","properties":{"id":null,"id_bollettino":202603032,"data_bollettino":"2026-03-03Z","id_fenomeno":1,"lat":43.278438517695925,"lon":13.10351039432027}},{"type":"Feature","id":"v_fenomeni_pub.fid--3eced7c9_19ca8b69bf0_-cbe","geometry":{"type":"Point","coordinates":[13.62668893,42.97001898]},"geometry_name":"geom","properties":{"id":null,"id_bollettino":202603032,"data_bollettino":"2026-03-03Z","id_fenomeno":1,"lat":42.970018977954915,"lon":13.626688933274918}},{"type":"Feature","id":"v_fenomeni_pub.fid--3eced7c9_19ca8b69bf0_-cbd","geometry":{"type":"Point","coordinates":[14.53219025,42.27411637]},"geometry_name":"geom","properties":{"id":null,"id_bollettino":202603032,"data_bollettino":"2026-03-03Z","id_fenomeno":1,"lat":42.274116365911055,"lon":14.53219025069642}},{"type":"Feature","id":"v_fenomeni_pub.fid--3eced7c9_19ca8b69bf0_-cbc","geometry":{"type":"Point","coordinates":[13.62668893,42.1399715]},"geometry_name":"geom","properties":{"id":null,"id_bollettino":202603032,"data_bollettino":"2026-03-03Z","id_fenomeno":1,"lat":42.13997149586569,"lon":13.626688933274918}},{"type":"Feature","id":"v_fenomeni_pub.fid--3eced7c9_19ca8b69bf0_-cbb","geometry":{"type":"Point","coordinates":[8.67661506,38.78842117]},"geometry_name":"geom","properties":{"id":null,"id_bollettino":202603032,"data_bollettino":"2026-03-03Z","id_fenomeno":10,"lat":38.788421166957505,"lon":8.676615064702782}},{"type":"Feature","id":"v_fenomeni_pub.fid--3eced7c9_19ca8b69bf0_-cba","geometry":{"type":"Point","coordinates":[9.21991586,41.5101989]},"geometry_name":"geom","properties":{"id":null,"id_bollettino":202603032,"data_bollettino":"2026-03-03Z","id_fenomeno":10,"lat":41.5101988990425,"lon":9.21991585515604}},{"type":"Feature","id":"v_fenomeni_pub.fid--3eced7c9_19ca8b69bf0_-cb9","geometry":{"type":"Point","coordinates":[7.61013574,40.61507293]},"geometry_name":"geom","properties":{"id":null,"id_bollettino":202603032,"data_bollettino":"2026-03-03Z","id_fenomeno":40,"lat":40.61507293026715,"lon":7.610135735294875}},{"type":"Feature","id":"v_fenomeni_pub.fid--3eced7c9_19ca8b69bf0_-cb8","geometry":{"type":"Point","coordinates":[7.59001348,39.61484752]},"geometry_name":"geom","properties":{"id":null,"id_bollettino":202603032,"data_bollettino":"2026-03-03Z","id_fenomeno":40,"lat":39.61484752197075,"lon":7.5900134837966196}},{"type":"Feature","id":"v_fenomeni_pub.fid--3eced7c9_19ca8b69bf0_-cb7","geometry":{"type":"Point","coordinates":[7.73086924,38.23735026]},"geometry_name":"geom","properties":{"id":null,"id_bollettino":202603032,"data_bollettino":"2026-03-03Z","id_fenomeno":40,"lat":38.237350260592414,"lon":7.730869244284499}},{"type":"Feature","id":"v_fenomeni_pub.fid--3eced7c9_19ca8b69bf0_-cb6","geometry":{"type":"Point","coordinates":[9.64248314,38.18991952]},"geometry_name":"geom","properties":{"id":null,"id_bollettino":202603032,"data_bollettino":"2026-03-03Z","id_fenomeno":40,"lat":38.18991951870067,"lon":9.642483136619411}},{"type":"Feature","id":"v_fenomeni_pub.fid--3eced7c9_19ca8b69bf0_-cb5","geometry":{"type":"Point","coordinates":[10.72908472,39.86242116]},"geometry_name":"geom","properties":{"id":null,"id_bollettino":202603032,"data_bollettino":"2026-03-03Z","id_fenomeno":40,"lat":39.86242115589275,"lon":10.729084717525211}},{"type":"Feature","id":"v_fenomeni_pub.fid--3eced7c9_19ca8b69bf0_-cb4","geometry":{"type":"Point","coordinates":[11.51385253,38.85113189]},"geometry_name":"geom","properties":{"id":null,"id_bollettino":202603032,"data_bollettino":"2026-03-03Z","id_fenomeno":40,"lat":38.85113188584357,"lon":11.513852525957182}},{"type":"Feature","id":"v_fenomeni_pub.fid--3eced7c9_19ca8b69bf0_-cb3","geometry":{"type":"Point","coordinates":[11.13152975,37.33089352]},"geometry_name":"geom","properties":{"id":null,"id_bollettino":202603032,"data_bollettino":"2026-03-03Z","id_fenomeno":40,"lat":37.33089351816151,"lon":11.131529747490323}},{"type":"Feature","id":"v_fenomeni_pub.fid--3eced7c9_19ca8b69bf0_-cb2","geometry":{"type":"Point","coordinates":[13.30473291,36.5751325]},"geometry_name":"geom","properties":{"id":null,"id_bollettino":202603032,"data_bollettino":"2026-03-03Z","id_fenomeno":40,"lat":36.57513249823665,"lon":13.304732909302828}},{"type":"Feature","id":"v_fenomeni_pub.fid--3eced7c9_19ca8b69bf0_-cb1","geometry":{"type":"Point","coordinates":[8.75710407,37.28287777]},"geometry_name":"geom","properties":{"id":null,"id_bollettino":202603032,"data_bollettino":"2026-03-03Z","id_fenomeno":40,"lat":37.28287776548479,"lon":8.757104070695805}},{"type":"Feature","id":"v_fenomeni_pub.fid--3eced7c9_19ca8b69bf0_-cb0","geometry":{"type":"Point","coordinates":[9.1193046,45.08205967]},"geometry_name":"geom","properties":{"id":null,"id_bollettino":202603032,"data_bollettino":"2026-03-03Z","id_fenomeno":30,"lat":45.082059668411276,"lon":9.119304597664765}},{"type":"Feature","id":"v_fenomeni_pub.fid--3eced7c9_19ca8b69bf0_-caf","geometry":{"type":"Point","coordinates":[10.5278622,44.93980112]},"geometry_name":"geom","properties":{"id":null,"id_bollettino":202603032,"data_bollettino":"2026-03-03Z","id_fenomeno":30,"lat":44.93980111986457,"lon":10.527862202542655}},{"type":"Feature","id":"v_fenomeni_pub.fid--3eced7c9_19ca8b69bf0_-cae","geometry":{"type":"Point","coordinates":[10.97055174,45.46439283]},"geometry_name":"geom","properties":{"id":null,"id_bollettino":202603032,"data_bollettino":"2026-03-03Z","id_fenomeno":30,"lat":45.46439282641077,"lon":10.97055173550428}},{"type":"Feature","id":"v_fenomeni_pub.fid--3eced7c9_19ca8b69bf0_-cad","geometry":{"type":"Point","coordinates":[11.7754418,44.68284531]},"geometry_name":"geom","properties":{"id":null,"id_bollettino":202603032,"data_bollettino":"2026-03-03Z","id_fenomeno":30,"lat":44.682845308803,"lon":11.775441795435404}},{"type":"Feature","id":"v_fenomeni_pub.fid--3eced7c9_19ca8b69bf0_-cac","geometry":{"type":"Point","coordinates":[12.41935384,44.12218076]},"geometry_name":"geom","properties":{"id":null,"id_bollettino":202603032,"data_bollettino":"2026-03-03Z","id_fenomeno":30,"lat":44.122180761269796,"lon":12.41935384337958}},{"type":"Feature","id":"v_fenomeni_pub.fid--3eced7c9_19ca8b69bf0_-cab","geometry":{"type":"Point","coordinates":[13.20412165,43.49778594]},"geometry_name":"geom","properties":{"id":null,"id_bollettino":202603032,"data_bollettino":"2026-03-03Z","id_fenomeno":30,"lat":43.497785942218414,"lon":13.20412165181155}},{"type":"Feature","id":"v_fenomeni_pub.fid--3eced7c9_19ca8b69bf0_-caa","geometry":{"type":"Point","coordinates":[14.12974522,42.58601285]},"geometry_name":"geom","properties":{"id":null,"id_bollettino":202603032,"data_bollettino":"2026-03-03Z","id_fenomeno":30,"lat":42.58601284552766,"lon":14.129745220731309}},{"type":"Feature","id":"v_fenomeni_pub.fid--3eced7c9_19ca8b69bf0_-ca9","geometry":{"type":"Point","coordinates":[15.03524654,41.97562992]},"geometry_name":"geom","properties":{"id":null,"id_bollettino":202603032,"data_bollettino":"2026-03-03Z","id_fenomeno":30,"lat":41.975629923532296,"lon":15.035246538153709}},{"type":"Feature","id":"v_fenomeni_pub.fid--3eced7c9_19ca8b69bf0_-ca8","geometry":{"type":"Point","coordinates":[15.53830283,41.2686573]},"geometry_name":"geom","properties":{"id":null,"id_bollettino":202603032,"data_bollettino":"2026-03-03Z","id_fenomeno":30,"lat":41.26865729673949,"lon":15.538302825610096}},{"type":"Feature","id":"v_fenomeni_pub.fid--3eced7c9_19ca8b69bf0_-ca7","geometry":{"type":"Point","coordinates":[16.78588242,40.88945338]},"geometry_name":"geom","properties":{"id":null,"id_bollettino":202603032,"data_bollettino":"2026-03-03Z","id_fenomeno":30,"lat":40.88945337619083,"lon":16.785882418501945}},{"type":"Feature","id":"v_fenomeni_pub.fid--3eced7c9_19ca8b69bf0_-ca6","geometry":{"type":"Point","coordinates":[18.07370651,40.1706364]},"geometry_name":"geom","properties":{"id":null,"id_bollettino":202603032,"data_bollettino":"2026-03-03Z","id_fenomeno":30,"lat":40.17063640002613,"lon":18.0737065143912}},{"type":"Feature","id":"v_fenomeni_pub.fid--3eced7c9_19ca8b69bf0_-ca5","geometry":{"type":"Point","coordinates":[16.04135911,40.46215034]},"geometry_name":"geom","properties":{"id":null,"id_bollettino":202603032,"data_bollettino":"2026-03-03Z","id_fenomeno":30,"lat":40.46215034367248,"lon":16.041359113066488}},{"type":"Feature","id":"v_fenomeni_pub.fid--3eced7c9_19ca8b69bf0_-ca4","geometry":{"type":"Point","coordinates":[11.05104074,43.48318748]},"geometry_name":"geom","properties":{"id":null,"id_bollettino":202603032,"data_bollettino":"2026-03-03Z","id_fenomeno":30,"lat":43.48318747717015,"lon":11.051040741497301}},{"type":"Feature","id":"v_fenomeni_pub.fid--3eced7c9_19ca8b69bf0_-ca3","geometry":{"type":"Point","coordinates":[11.99678656,43.26378714]},"geometry_name":"geom","properties":{"id":null,"id_bollettino":202603032,"data_bollettino":"2026-03-03Z","id_fenomeno":30,"lat":43.26378713546667,"lon":11.996786561916213}},{"type":"Feature","id":"v_fenomeni_pub.fid--3eced7c9_19ca8b69bf0_-ca2","geometry":{"type":"Point","coordinates":[12.76143212,42.82260615]},"geometry_name":"geom","properties":{"id":null,"id_bollettino":202603032,"data_bollettino":"2026-03-03Z","id_fenomeno":30,"lat":42.82260614918025,"lon":12.761432118849926}},{"type":"Feature","id":"v_fenomeni_pub.fid--3eced7c9_19ca8b69bf0_-ca1","geometry":{"type":"Point","coordinates":[9.8235834,45.42203856]},"geometry_name":"geom","properties":{"id":null,"id_bollettino":202603032,"data_bollettino":"2026-03-03Z","id_fenomeno":30,"lat":45.422038560416865,"lon":9.82358340010371}},{"type":"Feature","id":"v_fenomeni_pub.fid--3eced7c9_19ca8b69bf0_-ca0","geometry":{"type":"Point","coordinates":[12.19800908,45.28062802]},"geometry_name":"geom","properties":{"id":null,"id_bollettino":202603032,"data_bollettino":"2026-03-03Z","id_fenomeno":31,"lat":45.280628020087605,"lon":12.198009076898769}},{"type":"Feature","id":"v_fenomeni_pub.fid--3eced7c9_19ca8b69bf0_-c9f","geometry":{"type":"Point","coordinates":[13.12363265,45.74594205]},"geometry_name":"geom","properties":{"id":null,"id_bollettino":202603032,"data_bollettino":"2026-03-03Z","id_fenomeno":31,"lat":45.745942052492516,"lon":13.123632645818526}}],"crs":{"type":"name","properties":{"name":"urn:ogc:def:crs:EPSG::4326"}}}